[
  {
    "company_name": "PlaySimple Games Pvt. Ltd",
    "drive_month": "January 2025",
    "drive_type": "Virtual",
    "drive_dates": "\u25cf PPT will happen on 28th Jan, 25 \u25cf 31 st Jan 2025",
    "company_website": "www.playsimple.in linkedin https://www.linkedin.com/company/playsimple-games/",
    "stream_required": "B.E / B.Tech (CS, IT, ECE)",
    "eligibility": [
      "\u2022 CGPA/Percentage",
      "cut off : 6.5 (10th + 12th + Engineering - All semesters)"
    ],
    "batch": "2026",
    "roles_offered": [
      "Business Analyst",
      "Software Engineer"
    ],
    "job_location": "Bangalore",
    "date_of_joining": "June/July 2025",
    "package_salary": {
      "stipend": "",
      "ppo_ctc": "\u2022 Stipend during 1 year Internship : Rs 30,000 per month \u2022 Salary after 1 year Internship will be as under : CTC 14 LPA (13 LPA Fixed + 1 lac Variable) + Retention Bonus Components Monthly Annual Basic 43,333 520,000 HRA 17,333 208,000 Tel Allow 2,000 24,000 LTA 3,610 43,316 Spl. Allow. 38,173 458,072 Fixed Components 104,449 1,253,388 PF contribution (employer) 1,800 21,600 Gratuity (4.81% of basic) 2,084 25,012 Total 108,333 1,300,000 Variable Pay (Bonus / Incentives) 100,000 Total CTC 1,400,000 1st Year Retention Bonus 2,00,000 2nd Year Retention Bonus 3,00,000 3rd Year Retention Bonus 4,00,000",
      "bond": "No"
    },
    "selection_process_steps": [
      "\u2022 Campus Presentation (60-90 Minutes) & Online",
      "Test (45-60 Minutes)",
      "\u2022 Technical Interviews (2 Tech rounds + 1 Co-founder round + HR",
      "Discussion)"
     
    ],
    "category": "tech_roles"
  }
]