[
  {
    "company_name": "POD.ai (Calyxpod Talent Solutions Pvt. Ltd.)",
    "drive_month": "December 2025",
    "drive_type": "Virtual",
    "drive_dates": "2nd Week of Jan 2026 (tentative)",
    "company_website": "https://www.pod.ai/",
    "stream_required": "B.Tech, B.Com, BBA, MBA (All streams)",
    "eligibility": [
      "60% throughout"
    ],
    "batch": "2026",
    "roles_offered": [
      "Inside Sales Strategist"
    ],
    "job_location": "Gurugram - Work from the office (2 Saturdays in a month are working)",
    "date_of_joining": "Jan 2026 Onwards (Leaves will be allowed for exams)",
    "package_salary": {
      "stipend": "",
      "ppo_ctc": "Stipend during 6 months of Internship (for all courses) : Rs 18,000 per month Salary after 6 months of Internship will be as under : \u2192 For Graduates : INR 3.75 L.P.A.(Fixed) + Incentives \u2192 For Post Graduates : INR 4.25 L.P.A.(Fixed) + Incentives",
      "bond": "If the student does not wish to join Calyxpod Talent Solutions Pvt Ltd post successful completion of the internship, or leaves before 6 Months after starting full-time employment, he/she will be entitled to pay an amount of INR 50,000 to Calyxpod Talent Solutions Pvt Ltd. The bond condition is also applicable in case he/she doesn\u2019t complete the entire internship duration and chooses to leave in between. A signed cheque of INR 50,000 in the name of \u201cCalyxpod Talent Solutions Pvt Ltd\u201d has to be submitted as a security. This shall be returned to him/her post-completion of 6 months of full-time employment."
    },
    "selection_process_steps": [
      "2 Rounds of interviews",
      "\u00b7 Psychometric test",
      "\u00b7 PI"
    ],
    "category": "non_tech_roles"
  }
]