[
  {
    "company_name": "Qualhon Informatics Pvt. Ltd.",
    "drive_month": "December 2025",
    "drive_type": "Virtual",
    "drive_dates": "Will be intimated later",
    "company_website": "https://qualhon.com/",
    "stream_required": "\u25cf B.E / B.Tech (CSE, IT), BCA, MCA \u25cf MBA (Marketing), BBA \u25cf MBA (Marketing), BBA",
    "eligibility": [
      "Graduate"
    ],
    "batch": "2026",
    "roles_offered": [
      "\u25cf UI",
      "UX Designer",
      "\u25cf Python AI",
      "ML Developer",
      "\u25cf Full Stack Web Developer (MEAN)",
      "\u25cf Quality Assurance Intern",
      "\u25cf Digital Marketing Executive",
      "\u25cf Business Development Executive"
    ],
    "job_location": "2nd Floor, Plot No.1205C, Sector 82, JLPL Industrial , Area, Sahibzada Ajit Singh Nagar, Punjab 140306",
    "date_of_joining": "January 2026 (leaves will be provided for examination)",
    "package_salary": {
      "stipend": "",
      "ppo_ctc": "Rs 25,000/- per month from Day 1",
      "bond": "No Bond or Fee charges"
    },
    "selection_process_steps": [
      "3 Round Interview"
     
    ],
    "category": "tech_roles"
  }
]